his_geo/__init__.py
his_geo/calculator.py
his_geo/detector.py
his_geo/extractor.py
his_geo/geocoder.py
his_geo/matcher.py
his_geo/normalizer.py
his_geo/data/direction.json
his_geo/data/minority_list.txt
his_geo/data/Historic/compute_tgaz_level.ipynb
his_geo/data/Historic/gazetteer_chgis.csv
his_geo/data/Historic/tgaz_chgis.csv
his_geo/data/Historic/tgaz_chgis_with_level.csv
his_geo/data/Historic/v6_time_cnty_pts_gbk_wgs84.csv
his_geo/data/Historic/v6_time_pref_pgn_utf_wgs84.csv
his_geo/data/Historic/v6_time_pref_pts_utf_wgs84.csv
his_geo/data/Modern/2020China.geojson
his_geo/data/Modern/2020ChinaCountyTable.csv
his_geo/data/Modern/ModernChinaCountyTable.csv
his_geo/data/Modern/diff.json
his_geo/data/Modern/history.json
his_geo/data/Modern/history_mapping.ipynb
his_geo/utils/__init__.py
his_geo/utils/calculation/__init__.py
his_geo/utils/calculation/point_to_point.py
his_geo/utils/calculation/polygon_to_point.py
his_geo/utils/detection/__init__.py
his_geo/utils/detection/direction_detection_ch.py
his_geo/utils/extraction/__init__.py
his_geo/utils/extraction/chatgpt_extractor.py
his_geo/utils/matching/__init__.py
his_geo/utils/matching/hierarchical_matching_ch_his.py
his_geo/utils/matching/hierarchical_matching_ch_his_archive.py
his_geo/utils/matching/hierarchical_matching_ch_modern.py
his_geo/utils/normalization/__init__.py
his_geo/utils/normalization/normalization_ch_his.py
his_geo/utils/normalization/normalization_ch_modern.py
his_geo-0.1.6.dist-info/LICENSE
his_geo-0.1.6.dist-info/METADATA
his_geo-0.1.6.dist-info/WHEEL
his_geo-0.1.6.dist-info/top_level.txt
his_geo-0.1.6.dist-info/RECORD
