Metadata-Version: 2.1
Name: his_geo
Version: 0.1.6
Summary: A library to extract historical toponyms from texts, geocode and visualize the results.
Author: Yuqi Chen
Author-email: cyq0722@pku.edu.cn
License-File: LICENSE
Requires-Dist: pandas
Requires-Dist: geopandas
Requires-Dist: geopy
Requires-Dist: shapely
Requires-Dist: openai
Requires-Dist: keplergl
Requires-Dist: setuptools
Requires-Dist: pandarallel
